pydicttools/__init__.py
pydicttools/pydicttools.py
pydicttools-0.1.0.dist-info/METADATA
pydicttools-0.1.0.dist-info/WHEEL
pydicttools-0.1.0.dist-info/LICENSE
pydicttools-0.1.0.dist-info/RECORD
