Metadata-Version: 2.1
Name: pydicttools
Version: 0.1.0
Summary: Set of tools to handle Dict type in Python.
Home-page: https://github.com/fadedreams/pydicttools
License: MIT
Keywords: regex,utilities
Author: fadedreams7
Author-email: fadedreams7@gmail.com
Requires-Python: >=3.8,<4.0
Classifier: Environment :: Console
Classifier: License :: OSI Approved :: MIT License
Classifier: Operating System :: OS Independent
Classifier: Programming Language :: Python :: 3
Classifier: Programming Language :: Python :: 3.8
Classifier: Programming Language :: Python :: 3.9
Classifier: Programming Language :: Python :: 3.10
Classifier: Programming Language :: Python :: 3.11
Classifier: Programming Language :: Python :: 3
Classifier: Topic :: Utilities
Requires-Dist: asyncio (>=3.4.3,<4.0.0)
Requires-Dist: pytest (>=7.2.1,<8.0.0)
Requires-Dist: pytest-asyncio (>=0.20.3,<0.21.0)
Project-URL: Repository, https://github.com/fadedreams/pydicttools
